{"learner":{"attributes":{"scikit_learn":"{\"_estimator_type\": \"classifier\"}"},"feature_names":[],"feature_types":[],"gradient_booster":{"model":{"cats":{"enc":[],"feature_segments":[],"sorted_idx":[]},"gbtree_model_param":{"num_parallel_tree":"1","num_trees":"50"},"iteration_indptr":[0,1,2,3,4,5,6,7,8,9,10,11,12,13,14,15,16,17,18,19,20,21,22,23,24,25,26,27,28,29,30,31,32,33,34,35,36,37,38,39,40,41,42,43,44,45,46,47,48,49,50],"tree_info":[0,0,0,0,0,0,0,0,0,0,0,0,0,0,0,0,0,0,0,0,0,0,0,0,0,0,0,0,0,0,0,0,0,0,0,0,0,0,0,0,0,0,0,0,0,0,0,0,0,0],"trees":[{"base_weights":[1.2724585E-7,1.9053291E-1,-1.9041358E-1],"categories":[],"categories_nodes":[],"categories_segments":[],"categories_sizes":[],"default_left":[0,0,0],"id":0,"left_children":[1,-1,-1],"loss_changes":[1.5232848E2,0E0,0E0],"parents":[2147483647,0,0],"right_children":[2,-1,-1],"split_conditions":[7.660925E-1,1.9053291E-1,-1.9041358E-1],"split_indices":[8,0,0],"split_type":[0,0,0],"sum_hessian":[3.9986847E1,1.9986847E1,1.9999998E1],"tree_param":{"num_deleted":"0","num_feature":"30","num_nodes":"3","size_leaf_vector":"1"}},{"base_weights":[-2.4501282E-6,1.7392556E-1,-1.73836E-1],"categories":[],"categories_nodes":[],"categories_segments":[],"categories_sizes":[],"default_left":[0,0,0],"id":1,"left_children":[1,-1,-1],"loss_changes":[1.2585527E2,0E0,0E0],"parents":[2147483647,0,0],"right_children":[2,-1,-1],"split_conditions":[7.660925E-1,1.7392556E-1,-1.73836E-1],"split_indices":[8,0,0],"split_type":[0,0,0],"sum_hessian":[3.9626347E1,1.9807785E1,1.9818562E1],"tree_param":{"num_deleted":"0","num_feature":"30","num_nodes":"3","size_leaf_vector":"1"}},{"base_weights":[-3.863404E-6,1.6116944E-1,-1.6109997E-1],"categories":[],"categories_nodes":[],"categories_segments":[],"categories_sizes":[],"default_left":[0,0,0],"id":2,"left_children":[1,-1,-1],"loss_changes":[1.0564537E2,0E0,0E0],"parents":[2147483647,0,0],"right_children":[2,-1,-1],"split_conditions":[7.660925E-1,1.6116944E-1,-1.6109997E-1],"split_indices":[8,0,0],"split_type":[0,0,0],"sum_hessian":[3.8688564E1,1.933985E1,1.9348715E1],"tree_param":{"num_deleted":"0","num_feature":"30","num_nodes":"3","size_leaf_vector":"1"}},{"base_weights":[-4.647309E-6,1.510662E-1,-1.51011E-1],"categories":[],"categories_nodes":[],"categories_segments":[],"categories_sizes":[],"default_left":[0,0,0],"id":3,"left_children":[1,-1,-1],"loss_changes":[8.9764656E1,0E0,0E0],"parents":[2147483647,0,0],"right_children":[2,-1,-1],"split_conditions":[7.660925E-1,1.510662E-1,-1.51011E-1],"split_indices":[8,0,0],"split_type":[0,0,0],"sum_hessian":[3.7348618E1,1.8670656E1,1.8677961E1],"tree_param":{"num_deleted":"0","num_feature":"30","num_nodes":"3","size_leaf_vector":"1"}},{"base_weights":[-4.8792936E-6,1.4286658E-1,-1.4282185E-1],"categories":[],"categories_nodes":[],"categories_segments":[],"categories_sizes":[],"default_left":[0,0,0],"id":4,"left_children":[1,-1,-1],"loss_changes":[7.700468E1,0E0,0E0],"parents":[2147483647,0,0],"right_children":[2,-1,-1],"split_conditions":[7.660925E-1,1.4286658E-1,-1.4282185E-1],"split_indices":[8,0,0],"split_type":[0,0,0],"sum_hessian":[3.5739124E1,1.7866545E1,1.787258E1],"tree_param":{"num_deleted":"0","num_feature":"30","num_nodes":"3","size_leaf_vector":"1"}},{"base_weights":[-4.986848E-6,1.3607655E-1,-1.3603978E-1],"categories":[],"categories_nodes":[],"categories_segments":[],"categories_sizes":[],"default_left":[0,0,0],"id":5,"left_children":[1,-1,-1],"loss_changes":[6.656978E1,0E0,0E0],"parents":[2147483647,0,0],"right_children":[2,-1,-1],"split_conditions":[7.660925E-1,1.3607655E-1,-1.3603978E-1],"split_indices":[8,0,0],"split_type":[0,0,0],"sum_hessian":[3.396068E1,1.6977844E1,1.6982834E1],"tree_param":{"num_deleted":"0","num_feature":"30","num_nodes":"3","size_leaf_vector":"1"}},{"base_weights":[-4.8388033E-6,1.3035639E-1,-1.3032575E-1],"categories":[],"categories_nodes":[],"categories_segments":[],"categories_sizes":[],"default_left":[0,0,0],"id":6,"left_children":[1,-1,-1],"loss_changes":[5.791374E1,0E0,0E0],"parents":[2147483647,0,0],"right_children":[2,-1,-1],"split_conditions":[7.660925E-1,1.3035639E-1,-1.3032575E-1],"split_indices":[8,0,0],"split_type":[0,0,0],"sum_hessian":[3.2089375E1,1.6042624E1,1.6046753E1],"tree_param":{"num_deleted":"0","num_feature":"30","num_nodes":"3","size_leaf_vector":"1"}},{"base_weights":[-4.6998634E-6,1.2546417E-1,-1.2543838E-1],"categories":[],"categories_nodes":[],"categories_segments":[],"categories_sizes":[],"default_left":[0,0,0],"id":7,"left_children":[1,-1,-1],"loss_changes":[5.0648693E1,0E0,0E0],"parents":[2147483647,0,0],"right_children":[2,-1,-1],"split_conditions":[7.660925E-1,1.2546417E-1,-1.2543838E-1],"split_indices":[8,0,0],"split_type":[0,0,0],"sum_hessian":[3.0182379E1,1.5089478E1,1.5092902E1],"tree_param":{"num_deleted":"0","num_feature":"30","num_nodes":"3","size_leaf_vector":"1"}},{"base_weights":[-4.5646725E-6,1.2122264E-1,-1.2120078E-1],"categories":[],"categories_nodes":[],"categories_segments":[],"categories_sizes":[],"default_left":[0,0,0],"id":8,"left_children":[1,-1,-1],"loss_changes":[4.449138E1,0E0,0E0],"parents":[2147483647,0,0],"right_children":[2,-1,-1],"split_conditions":[7.660925E-1,1.2122264E-1,-1.2120078E-1],"split_indices":[8,0,0],"split_type":[0,0,0],"sum_hessian":[2.8282148E1,1.4139654E1,1.4142495E1],"tree_param":{"num_deleted":"0","num_feature":"30","num_nodes":"3","size_leaf_vector":"1"}},{"base_weights":[-4.3339887E-6,1.1749872E-1,-1.1748003E-1],"categories":[],"categories_nodes":[],"categories_segments":[],"categories_sizes":[],"default_left":[0,0,0],"id":9,"left_children":[1,-1,-1],"loss_changes":[3.9229877E1,0E0,0E0],"parents":[2147483647,0,0],"right_children":[2,-1,-1],"split_conditions":[7.660925E-1,1.1749872E-1,-1.1748003E-1],"split_indices":[8,0,0],"split_type":[0,0,0],"sum_hessian":[2.641972E1,1.3208679E1,1.32110405E1],"tree_param":{"num_deleted":"0","num_feature":"30","num_nodes":"3","size_leaf_vector":"1"}},{"base_weights":[-4.1037883E-6,1.1419026E-1,-1.1417419E-1],"categories":[],"categories_nodes":[],"categories_segments":[],"categories_sizes":[],"default_left":[0,0,0],"id":10,"left_children":[1,-1,-1],"loss_changes":[3.4702427E1,0E0,0E0],"parents":[2147483647,0,0],"right_children":[2,-1,-1],"split_conditions":[7.660925E-1,1.1419026E-1,-1.1417419E-1],"split_indices":[8,0,0],"split_type":[0,0,0],"sum_hessian":[2.4617231E1,1.2307633E1,1.2309598E1],"tree_param":{"num_deleted":"0","num_feature":"30","num_nodes":"3","size_leaf_vector":"1"}},{"base_weights":[-3.870321E-6,1.1121746E-1,-1.112036E-1],"categories":[],"categories_nodes":[],"categories_segments":[],"categories_sizes":[],"default_left":[0,0,0],"id":11,"left_children":[1,-1,-1],"loss_changes":[3.0783325E1,0E0,0E0],"parents":[2147483647,0,0],"right_children":[2,-1,-1],"split_conditions":[7.660925E-1,1.1121746E-1,-1.112036E-1],"split_indices":[8,0,0],"split_type":[0,0,0],"sum_hessian":[2.2889933E1,1.1444149E1,1.1445784E1],"tree_param":{"num_deleted":"0","num_feature":"30","num_nodes":"3","size_leaf_vector":"1"}},{"base_weights":[-3.5967332E-6,1.0851704E-1,-1.0850501E-1],"categories":[],"categories_nodes":[],"categories_segments":[],"categories_sizes":[],"default_left":[0,0,0],"id":12,"left_children":[1,-1,-1],"loss_changes":[2.7373398E1,0E0,0E0],"parents":[2147483647,0,0],"right_children":[2,-1,-1],"split_conditions":[7.660925E-1,1.0851704E-1,-1.0850501E-1],"split_indices":[8,0,0],"split_type":[0,0,0],"sum_hessian":[2.1247753E1,1.0623196E1,1.06245575E1],"tree_param":{"num_deleted":"0","num_feature":"30","num_nodes":"3","size_leaf_vector":"1"}},{"base_weights":[-3.0077308E-6,1.0603801E-1,-1.0602752E-1],"categories":[],"categories_nodes":[],"categories_segments":[],"categories_sizes":[],"default_left":[0,0,0],"id":13,"left_children":[1,-1,-1],"loss_changes":[2.4393295E1,0E0,0E0],"parents":[2147483647,0,0],"right_children":[2,-1,-1],"split_conditions":[7.660925E-1,1.0603801E-1,-1.0602752E-1],"split_indices":[8,0,0],"split_type":[0,0,0],"sum_hessian":[1.9696533E1,9.8477E0,9.848832E0],"tree_param":{"num_deleted":"0","num_feature":"30","num_nodes":"3","size_leaf_vector":"1"}},{"base_weights":[-2.8173506E-6,1.0373888E-1,-1.0372972E-1],"categories":[],"categories_nodes":[],"categories_segments":[],"categories_sizes":[],"default_left":[0,0,0],"id":14,"left_children":[1,-1,-1],"loss_changes":[2.1778778E1,0E0,0E0],"parents":[2147483647,0,0],"right_children":[2,-1,-1],"split_conditions":[7.660925E-1,1.0373888E-1,-1.0372972E-1],"split_indices":[8,0,0],"split_type":[0,0,0],"sum_hessian":[1.8238987E1,9.11902E0,9.1199665E0],"tree_param":{"num_deleted":"0","num_feature":"30","num_nodes":"3","size_leaf_vector":"1"}},{"base_weights":[-2.690469E-6,1.0158558E-1,-1.0157756E-1],"categories":[],"categories_nodes":[],"categories_segments":[],"categories_sizes":[],"default_left":[0,0,0],"id":15,"left_children":[1,-1,-1],"loss_changes":[1.9477287E1,0E0,0E0],"parents":[2147483647,0,0],"right_children":[2,-1,-1],"split_conditions":[7.660925E-1,1.0158558E-1,-1.0157756E-1],"split_indices":[8,0,0],"split_type":[0,0,0],"sum_hessian":[1.6875505E1,8.437357E0,8.438149E0],"tree_param":{"num_deleted":"0","num_feature":"30","num_nodes":"3","size_leaf_vector":"1"}},{"base_weights":[-2.1223589E-6,9.954993E-2,-9.954287E-2],"categories":[],"categories_nodes":[],"categories_segments":[],"categories_sizes":[],"default_left":[0,0,0],"id":16,"left_children":[1,-1,-1],"loss_changes":[1.7445404E1,0E0,0E0],"parents":[2147483647,0,0],"right_children":[2,-1,-1],"split_conditions":[7.660925E-1,9.954993E-2,-9.954287E-2],"split_indices":[8,0,0],"split_type":[0,0,0],"sum_hessian":[1.56047535E1,7.8020473E0,7.8027062E0],"tree_param":{"num_deleted":"0","num_feature":"30","num_nodes":"3","size_leaf_vector":"1"}},{"base_weights":[-1.6544383E-6,9.760843E-2,-9.760222E-2],"categories":[],"categories_nodes":[],"categories_segments":[],"categories_sizes":[],"default_left":[0,0,0],"id":17,"left_children":[1,-1,-1],"loss_changes":[1.564692E1,0E0,0E0],"parents":[2147483647,0,0],"right_children":[2,-1,-1],"split_conditions":[7.660925E-1,9.760843E-2,-9.760222E-2],"split_indices":[8,0,0],"split_type":[0,0,0],"sum_hessian":[1.442411E1,7.2117805E0,7.2123294E0],"tree_param":{"num_deleted":"0","num_feature":"30","num_nodes":"3","size_leaf_vector":"1"}},{"base_weights":[-2.090102E-6,9.574151E-2,-9.5736064E-2],"categories":[],"categories_nodes":[],"categories_segments":[],"categories_sizes":[],"default_left":[0,0,0],"id":18,"left_children":[1,-1,-1],"loss_changes":[1.4051423E1,0E0,0E0],"parents":[2147483647,0,0],"right_children":[2,-1,-1],"split_conditions":[7.660925E-1,9.574151E-2,-9.5736064E-2],"split_indices":[8,0,0],"split_type":[0,0,0],"sum_hessian":[1.3330082E1,6.6648073E0,6.6652746E0],"tree_param":{"num_deleted":"0","num_feature":"30","num_nodes":"3","size_leaf_vector":"1"}},{"base_weights":[-1.4936289E-6,9.393293E-2,-9.392811E-2],"categories":[],"categories_nodes":[],"categories_segments":[],"categories_sizes":[],"default_left":[0,0,0],"id":19,"left_children":[1,-1,-1],"loss_changes":[1.2633221E1,0E0,0E0],"parents":[2147483647,0,0],"right_children":[2,-1,-1],"split_conditions":[7.660925E-1,9.393293E-2,-9.392811E-2],"split_indices":[8,0,0],"split_type":[0,0,0],"sum_hessian":[1.23186035E1,6.159107E0,6.159496E0],"tree_param":{"num_deleted":"0","num_feature":"30","num_nodes":"3","size_leaf_vector":"1"}},{"base_weights":[-1.2632992E-6,9.21691E-2,-9.216484E-2],"categories":[],"categories_nodes":[],"categories_segments":[],"categories_sizes":[],"default_left":[0,0,0],"id":20,"left_children":[1,-1,-1],"loss_changes":[1.1370396E1,0E0,0E0],"parents":[2147483647,0,0],"right_children":[2,-1,-1],"split_conditions":[7.660925E-1,9.21691E-2,-9.216484E-2],"split_indices":[8,0,0],"split_type":[0,0,0],"sum_hessian":[1.1385205E1,5.692439E0,5.6927657E0],"tree_param":{"num_deleted":"0","num_feature":"30","num_nodes":"3","size_leaf_vector":"1"}},{"base_weights":[-6.8362885E-7,9.043888E-2,-9.043509E-2],"categories":[],"categories_nodes":[],"categories_segments":[],"categories_sizes":[],"default_left":[0,0,0],"id":21,"left_children":[1,-1,-1],"loss_changes":[1.0244205E1,0E0,0E0],"parents":[2147483647,0,0],"right_children":[2,-1,-1],"split_conditions":[7.660925E-1,9.043888E-2,-9.043509E-2],"split_indices":[8,0,0],"split_type":[0,0,0],"sum_hessian":[1.0525243E1,5.262486E0,5.262757E0],"tree_param":{"num_deleted":"0","num_feature":"30","num_nodes":"3","size_leaf_vector":"1"}},{"base_weights":[-7.340221E-7,8.873313E-2,-8.872979E-2],"categories":[],"categories_nodes":[],"categories_segments":[],"categories_sizes":[],"default_left":[0,0,0],"id":22,"left_children":[1,-1,-1],"loss_changes":[9.238493E0,0E0,0E0],"parents":[2147483647,0,0],"right_children":[2,-1,-1],"split_conditions":[7.660925E-1,8.873313E-2,-8.872979E-2],"split_indices":[8,0,0],"split_type":[0,0,0],"sum_hessian":[9.7339945E0,4.8668823E0,4.867112E0],"tree_param":{"num_deleted":"0","num_feature":"30","num_nodes":"3","size_leaf_vector":"1"}},{"base_weights":[-1.4518784E-7,8.704466E-2,-8.7041676E-2],"categories":[],"categories_nodes":[],"categories_segments":[],"categories_sizes":[],"default_left":[0,0,0],"id":23,"left_children":[1,-1,-1],"loss_changes":[8.339304E0,0E0,0E0],"parents":[2147483647,0,0],"right_children":[2,-1,-1],"split_conditions":[7.660925E-1,8.704466E-2,-8.7041676E-2],"split_indices":[8,0,0],"split_type":[0,0,0],"sum_hessian":[9.0067835E0,4.5032964E0,4.5034866E0],"tree_param":{"num_deleted":"0","num_feature":"30","num_nodes":"3","size_leaf_vector":"1"}},{"base_weights":[-1.7950272E-8,8.536774E-2,-8.53651E-2],"categories":[],"categories_nodes":[],"categories_segments":[],"categories_sizes":[],"default_left":[0,0,0],"id":24,"left_children":[1,-1,-1],"loss_changes":[7.534488E0,0E0,0E0],"parents":[2147483647,0,0],"right_children":[2,-1,-1],"split_conditions":[7.660925E-1,8.536774E-2,-8.53651E-2],"split_indices":[8,0,0],"split_type":[0,0,0],"sum_hessian":[8.339026E0,4.169433E0,4.1695933E0],"tree_param":{"num_deleted":"0","num_feature":"30","num_nodes":"3","size_leaf_vector":"1"}},{"base_weights":[-5.8485824E-7,8.369817E-2,-8.369585E-2],"categories":[],"categories_nodes":[],"categories_segments":[],"categories_sizes":[],"default_left":[0,0,0],"id":25,"left_children":[1,-1,-1],"loss_changes":[6.813456E0,0E0,0E0],"parents":[2147483647,0,0],"right_children":[2,-1,-1],"split_conditions":[7.660925E-1,8.369817E-2,-8.369585E-2],"split_indices":[8,0,0],"split_type":[0,0,0],"sum_hessian":[7.726299E0,3.8630788E0,3.86322E0],"tree_param":{"num_deleted":"0","num_feature":"30","num_nodes":"3","size_leaf_vector":"1"}},{"base_weights":[5.6807477E-7,8.2033075E-2,-8.203097E-2],"categories":[],"categories_nodes":[],"categories_segments":[],"categories_sizes":[],"default_left":[0,0,0],"id":26,"left_children":[1,-1,-1],"loss_changes":[6.166952E0,0E0,0E0],"parents":[2147483647,0,0],"right_children":[2,-1,-1],"split_conditions":[7.660925E-1,8.2033075E-2,-8.203097E-2],"split_indices":[8,0,0],"split_type":[0,0,0],"sum_hessian":[7.1643944E0,3.582141E0,3.5822532E0],"tree_param":{"num_deleted":"0","num_feature":"30","num_nodes":"3","size_leaf_vector":"1"}},{"base_weights":[-6.3311596E-8,8.037049E-2,-8.036865E-2],"categories":[],"categories_nodes":[],"categories_segments":[],"categories_sizes":[],"default_left":[0,0,0],"id":27,"left_children":[1,-1,-1],"loss_changes":[5.5867977E0,0E0,0E0],"parents":[2147483647,0,0],"right_children":[2,-1,-1],"split_conditions":[7.660925E-1,8.037049E-2,-8.036865E-2],"split_indices":[8,0,0],"split_type":[0,0,0],"sum_hessian":[6.6492743E0,3.3245873E0,3.324687E0],"tree_param":{"num_deleted":"0","num_feature":"30","num_nodes":"3","size_leaf_vector":"1"}},{"base_weights":[8.330693E-7,7.870974E-2,-7.870805E-2],"categories":[],"categories_nodes":[],"categories_segments":[],"categories_sizes":[],"default_left":[0,0,0],"id":28,"left_children":[1,-1,-1],"loss_changes":[5.065839E0,0E0,0E0],"parents":[2147483647,0,0],"right_children":[2,-1,-1],"split_conditions":[7.660925E-1,7.870974E-2,-7.870805E-2],"split_indices":[8,0,0],"split_type":[0,0,0],"sum_hessian":[6.177183E0,3.0885518E0,3.0886314E0],"tree_param":{"num_deleted":"0","num_feature":"30","num_nodes":"3","size_leaf_vector":"1"}},{"base_weights":[3.0102527E-7,7.705068E-2,-7.704921E-2],"categories":[],"categories_nodes":[],"categories_segments":[],"categories_sizes":[],"default_left":[0,0,0],"id":29,"left_children":[1,-1,-1],"loss_changes":[4.5977087E0,0E0,0E0],"parents":[2147483647,0,0],"right_children":[2,-1,-1],"split_conditions":[7.660925E-1,7.705068E-2,-7.704921E-2],"split_indices":[8,0,0],"split_type":[0,0,0],"sum_hessian":[5.744561E0,2.8722448E0,2.8723164E0],"tree_param":{"num_deleted":"0","num_feature":"30","num_nodes":"3","size_leaf_vector":"1"}},{"base_weights":[1.4201371E-6,7.5394206E-2,-7.539284E-2],"categories":[],"categories_nodes":[],"categories_segments":[],"categories_sizes":[],"default_left":[0,0,0],"id":30,"left_children":[1,-1,-1],"loss_changes":[4.1768064E0,0E0,0E0],"parents":[2147483647,0,0],"right_children":[2,-1,-1],"split_conditions":[7.660925E-1,7.5394206E-2,-7.539284E-2],"split_indices":[8,0,0],"split_type":[0,0,0],"sum_hessian":[5.348121E0,2.6740334E0,2.674088E0],"tree_param":{"num_deleted":"0","num_feature":"30","num_nodes":"3","size_leaf_vector":"1"}},{"base_weights":[1.5421468E-6,7.374154E-2,-7.37403E-2],"categories":[],"categories_nodes":[],"categories_segments":[],"categories_sizes":[],"default_left":[0,0,0],"id":31,"left_children":[1,-1,-1],"loss_changes":[3.798129E0,0E0,0E0],"parents":[2147483647,0,0],"right_children":[2,-1,-1],"split_conditions":[7.660925E-1,7.374154E-2,-7.37403E-2],"split_indices":[8,0,0],"split_type":[0,0,0],"sum_hessian":[4.9847784E0,2.492366E0,2.492412E0],"tree_param":{"num_deleted":"0","num_feature":"30","num_nodes":"3","size_leaf_vector":"1"}},{"base_weights":[1.3232353E-6,7.209451E-2,-7.209341E-2],"categories":[],"categories_nodes":[],"categories_segments":[],"categories_sizes":[],"default_left":[0,0,0],"id":32,"left_children":[1,-1,-1],"loss_changes":[3.4572434E0,0E0,0E0],"parents":[2147483647,0,0],"right_children":[2,-1,-1],"split_conditions":[7.660925E-1,7.209451E-2,-7.209341E-2],"split_indices":[8,0,0],"split_type":[0,0,0],"sum_hessian":[4.6516933E0,2.3258266E0,2.3258667E0],"tree_param":{"num_deleted":"0","num_feature":"30","num_nodes":"3","size_leaf_vector":"1"}},{"base_weights":[1.9736988E-6,7.045536E-2,-7.045433E-2],"categories":[],"categories_nodes":[],"categories_segments":[],"categories_sizes":[],"default_left":[0,0,0],"id":33,"left_children":[1,-1,-1],"loss_changes":[3.1502047E0,0E0,0E0],"parents":[2147483647,0,0],"right_children":[2,-1,-1],"split_conditions":[7.660925E-1,7.045536E-2,-7.045433E-2],"split_indices":[8,0,0],"split_type":[0,0,0],"sum_hessian":[4.3462486E0,2.1731088E0,2.1731398E0],"tree_param":{"num_deleted":"0","num_feature":"30","num_nodes":"3","size_leaf_vector":"1"}},{"base_weights":[1.4688586E-6,6.882642E-2,-6.882552E-2],"categories":[],"categories_nodes":[],"categories_segments":[],"categories_sizes":[],"default_left":[0,0,0],"id":34,"left_children":[1,-1,-1],"loss_changes":[2.8734825E0,0E0,0E0],"parents":[2147483647,0,0],"right_children":[2,-1,-1],"split_conditions":[7.660925E-1,6.882642E-2,-6.882552E-2],"split_indices":[8,0,0],"split_type":[0,0,0],"sum_hessian":[4.06602E0,2.0329957E0,2.0330243E0],"tree_param":{"num_deleted":"0","num_feature":"30","num_nodes":"3","size_leaf_vector":"1"}},{"base_weights":[1.6849333E-6,6.72104E-2,-6.7209564E-2],"categories":[],"categories_nodes":[],"categories_segments":[],"categories_sizes":[],"default_left":[0,0,0],"id":35,"left_children":[1,-1,-1],"loss_changes":[2.6239402E0,0E0,0E0],"parents":[2147483647,0,0],"right_children":[2,-1,-1],"split_conditions":[7.660925E-1,6.72104E-2,-6.7209564E-2],"split_indices":[8,0,0],"split_type":[0,0,0],"sum_hessian":[3.8087995E0,1.9043878E0,1.9044116E0],"tree_param":{"num_deleted":"0","num_feature":"30","num_nodes":"3","size_leaf_vector":"1"}},{"base_weights":[1.313716E-6,6.5609865E-2,-6.560914E-2],"categories":[],"categories_nodes":[],"categories_segments":[],"categories_sizes":[],"default_left":[0,0,0],"id":36,"left_children":[1,-1,-1],"loss_changes":[2.3987632E0,0E0,0E0],"parents":[2147483647,0,0],"right_children":[2,-1,-1],"split_conditions":[7.660925E-1,6.5609865E-2,-6.560914E-2],"split_indices":[8,0,0],"split_type":[0,0,0],"sum_hessian":[3.5725489E0,1.7862636E0,1.7862854E0],"tree_param":{"num_deleted":"0","num_feature":"30","num_nodes":"3","size_leaf_vector":"1"}},{"base_weights":[6.1369553E-7,6.40275E-2,-6.4026885E-2],"categories":[],"categories_nodes":[],"categories_segments":[],"categories_sizes":[],"default_left":[0,0,0],"id":37,"left_children":[1,-1,-1],"loss_changes":[2.1954403E0,0E0,0E0],"parents":[2147483647,0,0],"right_children":[2,-1,-1],"split_conditions":[7.660925E-1,6.40275E-2,-6.4026885E-2],"split_indices":[8,0,0],"split_type":[0,0,0],"sum_hessian":[3.35541E0,1.6776943E0,1.6777159E0],"tree_param":{"num_deleted":"0","num_feature":"30","num_nodes":"3","size_leaf_vector":"1"}},{"base_weights":[2.648948E-6,6.246608E-2,-6.246539E-2],"categories":[],"categories_nodes":[],"categories_segments":[],"categories_sizes":[],"default_left":[0,0,0],"id":38,"left_children":[1,-1,-1],"loss_changes":[2.0117376E0,0E0,0E0],"parents":[2147483647,0,0],"right_children":[2,-1,-1],"split_conditions":[7.660925E-1,6.246608E-2,-6.246539E-2],"split_indices":[8,0,0],"split_type":[0,0,0],"sum_hessian":[3.1556995E0,1.5778444E0,1.5778552E0],"tree_param":{"num_deleted":"0","num_feature":"30","num_nodes":"3","size_leaf_vector":"1"}},{"base_weights":[1.7210907E-6,6.092767E-2,-6.09271E-2],"categories":[],"categories_nodes":[],"categories_segments":[],"categories_sizes":[],"default_left":[0,0,0],"id":39,"left_children":[1,-1,-1],"loss_changes":[1.8456221E0,0E0,0E0],"parents":[2147483647,0,0],"right_children":[2,-1,-1],"split_conditions":[7.660925E-1,6.092767E-2,-6.09271E-2],"split_indices":[8,0,0],"split_type":[0,0,0],"sum_hessian":[2.971846E0,1.485917E0,1.4859293E0],"tree_param":{"num_deleted":"0","num_feature":"30","num_nodes":"3","size_leaf_vector":"1"}},{"base_weights":[1.920224E-6,5.941484E-2,-5.9414297E-2],"categories":[],"categories_nodes":[],"categories_segments":[],"categories_sizes":[],"default_left":[0,0,0],"id":40,"left_children":[1,-1,-1],"loss_changes":[1.6953111E0,0E0,0E0],"parents":[2147483647,0,0],"right_children":[2,-1,-1],"split_conditions":[7.660925E-1,5.941484E-2,-5.9414297E-2],"split_indices":[8,0,0],"split_type":[0,0,0],"sum_hessian":[2.802457E0,1.4012237E0,1.4012334E0],"tree_param":{"num_deleted":"0","num_feature":"30","num_nodes":"3","size_leaf_vector":"1"}},{"base_weights":[2.7904587E-6,5.7929594E-2,-5.7929028E-2],"categories":[],"categories_nodes":[],"categories_segments":[],"categories_sizes":[],"default_left":[0,0,0],"id":41,"left_children":[1,-1,-1],"loss_changes":[1.5591897E0,0E0,0E0],"parents":[2147483647,0,0],"right_children":[2,-1,-1],"split_conditions":[7.660925E-1,5.7929594E-2,-5.7929028E-2],"split_indices":[8,0,0],"split_type":[0,0,0],"sum_hessian":[2.6462462E0,1.3231205E0,1.3231256E0],"tree_param":{"num_deleted":"0","num_feature":"30","num_nodes":"3","size_leaf_vector":"1"}},{"base_weights":[2.2312117E-6,5.647364E-2,-5.6473143E-2],"categories":[],"categories_nodes":[],"categories_segments":[],"categories_sizes":[],"default_left":[0,0,0],"id":42,"left_children":[1,-1,-1],"loss_changes":[1.4358108E0,0E0,0E0],"parents":[2147483647,0,0],"right_children":[2,-1,-1],"split_conditions":[7.660925E-1,5.647364E-2,-5.6473143E-2],"split_indices":[8,0,0],"split_type":[0,0,0],"sum_hessian":[2.5020418E0,1.251018E0,1.2510238E0],"tree_param":{"num_deleted":"0","num_feature":"30","num_nodes":"3","size_leaf_vector":"1"}},{"base_weights":[3.298116E-6,5.5048764E-2,-5.5048227E-2],"categories":[],"categories_nodes":[],"categories_segments":[],"categories_sizes":[],"default_left":[0,0,0],"id":43,"left_children":[1,-1,-1],"loss_changes":[1.3238921E0,0E0,0E0],"parents":[2147483647,0,0],"right_children":[2,-1,-1],"split_conditions":[7.660925E-1,5.5048764E-2,-5.5048227E-2],"split_indices":[8,0,0],"split_type":[0,0,0],"sum_hessian":[2.3687954E0,1.1843972E0,1.1843982E0],"tree_param":{"num_deleted":"0","num_feature":"30","num_nodes":"3","size_leaf_vector":"1"}},{"base_weights":[2.1349465E-6,5.365605E-2,-5.365562E-2],"categories":[],"categories_nodes":[],"categories_segments":[],"categories_sizes":[],"default_left":[0,0,0],"id":44,"left_children":[1,-1,-1],"loss_changes":[1.2222672E0,0E0,0E0],"parents":[2147483647,0,0],"right_children":[2,-1,-1],"split_conditions":[7.660925E-1,5.365605E-2,-5.365562E-2],"split_indices":[8,0,0],"split_type":[0,0,0],"sum_hessian":[2.2455332E0,1.1227646E0,1.1227686E0],"tree_param":{"num_deleted":"0","num_feature":"30","num_nodes":"3","size_leaf_vector":"1"}},{"base_weights":[2.4075719E-6,5.2296825E-2,-5.2296408E-2],"categories":[],"categories_nodes":[],"categories_segments":[],"categories_sizes":[],"default_left":[0,0,0],"id":45,"left_children":[1,-1,-1],"loss_changes":[1.1299098E0,0E0,0E0],"parents":[2147483647,0,0],"right_children":[2,-1,-1],"split_conditions":[7.660925E-1,5.2296825E-2,-5.2296408E-2],"split_indices":[8,0,0],"split_type":[0,0,0],"sum_hessian":[2.131394E0,1.0656959E0,1.0656981E0],"tree_param":{"num_deleted":"0","num_feature":"30","num_nodes":"3","size_leaf_vector":"1"}},{"base_weights":[8.034014E-7,5.0971698E-2,-5.097142E-2],"categories":[],"categories_nodes":[],"categories_segments":[],"categories_sizes":[],"default_left":[0,0,0],"id":46,"left_children":[1,-1,-1],"loss_changes":[1.0458848E0,0E0,0E0],"parents":[2147483647,0,0],"right_children":[2,-1,-1],"split_conditions":[7.660925E-1,5.0971698E-2,-5.097142E-2],"split_indices":[8,0,0],"split_type":[0,0,0],"sum_hessian":[2.0255759E0,1.0127848E0,1.0127912E0],"tree_param":{"num_deleted":"0","num_feature":"30","num_nodes":"3","size_leaf_vector":"1"}},{"base_weights":[1.8436357E-6],"categories":[],"categories_nodes":[],"categories_segments":[],"categories_sizes":[],"default_left":[0],"id":47,"left_children":[-1],"loss_changes":[0E0],"parents":[2147483647],"right_children":[-1],"split_conditions":[1.8436357E-7],"split_indices":[0],"split_type":[0],"sum_hessian":[1.9273757E0],"tree_param":{"num_deleted":"0","num_feature":"30","num_nodes":"1","size_leaf_vector":"1"}},{"base_weights":[1.8436357E-6],"categories":[],"categories_nodes":[],"categories_segments":[],"categories_sizes":[],"default_left":[0],"id":48,"left_children":[-1],"loss_changes":[0E0],"parents":[2147483647],"right_children":[-1],"split_conditions":[1.8436357E-7],"split_indices":[0],"split_type":[0],"sum_hessian":[1.9273757E0],"tree_param":{"num_deleted":"0","num_feature":"30","num_nodes":"1","size_leaf_vector":"1"}},{"base_weights":[1.8436357E-6],"categories":[],"categories_nodes":[],"categories_segments":[],"categories_sizes":[],"default_left":[0],"id":49,"left_children":[-1],"loss_changes":[0E0],"parents":[2147483647],"right_children":[-1],"split_conditions":[1.8436357E-7],"split_indices":[0],"split_type":[0],"sum_hessian":[1.9273757E0],"tree_param":{"num_deleted":"0","num_feature":"30","num_nodes":"1","size_leaf_vector":"1"}}]},"name":"gbtree"},"learner_model_param":{"base_score":"[4.9983555E-1]","boost_from_average":"1","num_class":"0","num_feature":"30","num_target":"1"},"objective":{"name":"binary:logistic","reg_loss_param":{"scale_pos_weight":"0.0525969751"}}},"version":[3,1,2]}